auto_mcp/__init__.py
auto_mcp/api.py
auto_mcp/cli.py
auto_mcp/config.py
auto_mcp/decorators.py
auto_mcp/watcher.py
auto_mcp/cache/__init__.py
auto_mcp/cache/file_cache.py
auto_mcp/core/__init__.py
auto_mcp/core/analyzer.py
auto_mcp/core/generator.py
auto_mcp/core/package.py
auto_mcp/isolation/__init__.py
auto_mcp/isolation/manager.py
auto_mcp/isolation/worker.py
auto_mcp/llm/__init__.py
auto_mcp/llm/anthropic.py
auto_mcp/llm/base.py
auto_mcp/llm/ollama.py
auto_mcp/llm/openai.py
auto_mcp/manifest/__init__.py
auto_mcp/manifest/dependencies.py
auto_mcp/manifest/generator.py
auto_mcp/manifest/resolver.py
auto_mcp/manifest/schema.py
auto_mcp/prompts/__init__.py
auto_mcp/prompts/templates.py
auto_mcp/session/__init__.py
auto_mcp/session/context.py
auto_mcp/session/decorators.py
auto_mcp/session/injection.py
auto_mcp/session/manager.py
auto_mcp/types/__init__.py
auto_mcp/types/adapters.py
auto_mcp/types/base.py
auto_mcp/types/compression.py
auto_mcp/types/registry.py
auto_mcp/types/store.py
auto_mcp/types/wrapper.py
auto_mcp/utils/__init__.py
auto_mcp/utils/logging.py
auto_mcp/wrapper/__init__.py
auto_mcp/wrapper/generator.py
auto_mcp/wrapper/type_mapper.py
auto_mcp_tool-0.2.1.dist-info/METADATA
auto_mcp_tool-0.2.1.dist-info/WHEEL
auto_mcp_tool-0.2.1.dist-info/entry_points.txt
auto_mcp_tool-0.2.1.dist-info/licenses/LICENSE
auto_mcp_tool-0.2.1.dist-info/RECORD
