Metadata-Version: 2.4
Name: auto-mcp-tool
Version: 0.2.1
Summary: Automatically generate MCP servers from Python modules using LLM-powered documentation
Project-URL: Homepage, https://github.com/krajasek/auto-mcp-framework
Project-URL: Documentation, https://github.com/krajasek/auto-mcp-framework#readme
Project-URL: Repository, https://github.com/krajasek/auto-mcp-framework.git
Project-URL: Issues, https://github.com/krajasek/auto-mcp-framework/issues
Project-URL: Changelog, https://github.com/krajasek/auto-mcp-framework/blob/main/CHANGELOG.md
Author-email: Karthik Rajasekaran <krajasek@gmail.com>
License-Expression: MIT
License-File: LICENSE
Keywords: ai,anthropic,automation,claude,code-generation,llm,mcp,model-context-protocol,ollama,openai,server,tools
Classifier: Development Status :: 4 - Beta
Classifier: Environment :: Console
Classifier: Intended Audience :: Developers
Classifier: License :: OSI Approved :: MIT License
Classifier: Operating System :: OS Independent
Classifier: Programming Language :: Python :: 3
Classifier: Programming Language :: Python :: 3.10
Classifier: Programming Language :: Python :: 3.11
Classifier: Programming Language :: Python :: 3.12
Classifier: Topic :: Scientific/Engineering :: Artificial Intelligence
Classifier: Topic :: Software Development :: Code Generators
Classifier: Topic :: Software Development :: Libraries :: Python Modules
Classifier: Typing :: Typed
Requires-Python: >=3.10
Requires-Dist: anthropic>=0.20
Requires-Dist: click>=8.0
Requires-Dist: mcp>=1.0
Requires-Dist: ollama>=0.3
Requires-Dist: openai>=1.0
Requires-Dist: pydantic-settings>=2.1.0
Requires-Dist: pydantic>=2.5.0
Requires-Dist: rich>=13.0.0
Requires-Dist: watchdog>=3.0
Provides-Extra: dev
Requires-Dist: mypy>=1.8.0; extra == 'dev'
Requires-Dist: numpy>=1.24.0; extra == 'dev'
Requires-Dist: pandas>=2.0.0; extra == 'dev'
Requires-Dist: pillow>=10.0.0; extra == 'dev'
Requires-Dist: pre-commit>=3.6.0; extra == 'dev'
Requires-Dist: pytest-asyncio>=0.23.0; extra == 'dev'
Requires-Dist: pytest-cov>=4.1.0; extra == 'dev'
Requires-Dist: pytest>=7.4.0; extra == 'dev'
Requires-Dist: ruff>=0.1.0; extra == 'dev'
